{
  "packageVersion": "1.0",
  "packageId": "de-c1-generated-erp-010-words",
  "packageName": "German C1 Generated ERP Batch 010",
  "source": "Hybrid",
  "defaultMeaningLanguages": [
    "ar",
    "ckb",
    "en",
    "fa",
    "kmr",
    "pl",
    "ro",
    "ru",
    "sq",
    "tr"
  ],
  "labels": [
    {
      "kind": "Usage",
      "key": "formal",
      "displayName": "Formal",
      "sortOrder": 20,
      "localizations": [
        {
          "language": "de",
          "name": "Formell"
        },
        {
          "language": "ar",
          "name": "رسمي"
        },
        {
          "language": "ckb",
          "name": "فەرمی"
        },
        {
          "language": "en",
          "name": "Formal"
        },
        {
          "language": "fa",
          "name": "رسمی"
        },
        {
          "language": "kmr",
          "name": "Fermî"
        },
        {
          "language": "pl",
          "name": "Formalny"
        },
        {
          "language": "ro",
          "name": "Formal"
        },
        {
          "language": "ru",
          "name": "Формальный"
        },
        {
          "language": "sq",
          "name": "Formal"
        },
        {
          "language": "tr",
          "name": "Resmi"
        }
      ]
    },
    {
      "kind": "Usage",
      "key": "business",
      "displayName": "Business",
      "sortOrder": 60,
      "localizations": [
        {
          "language": "de",
          "name": "Geschäftlich"
        },
        {
          "language": "ar",
          "name": "تجاري"
        },
        {
          "language": "ckb",
          "name": "بازرگانی"
        },
        {
          "language": "en",
          "name": "Business"
        },
        {
          "language": "fa",
          "name": "تجاری"
        },
        {
          "language": "kmr",
          "name": "Bazirganî"
        },
        {
          "language": "pl",
          "name": "Biznesowy"
        },
        {
          "language": "ro",
          "name": "De afaceri"
        },
        {
          "language": "ru",
          "name": "Деловой"
        },
        {
          "language": "sq",
          "name": "Biznesi"
        },
        {
          "language": "tr",
          "name": "İş"
        }
      ]
    },
    {
      "kind": "Usage",
      "key": "workplace",
      "displayName": "Workplace",
      "sortOrder": 70,
      "localizations": [
        {
          "language": "de",
          "name": "Am Arbeitsplatz"
        },
        {
          "language": "ar",
          "name": "في مكان العمل"
        },
        {
          "language": "ckb",
          "name": "لە شوێنی کار"
        },
        {
          "language": "en",
          "name": "Workplace"
        },
        {
          "language": "fa",
          "name": "محیط کار"
        },
        {
          "language": "kmr",
          "name": "Li cihê kar"
        },
        {
          "language": "pl",
          "name": "W miejscu pracy"
        },
        {
          "language": "ro",
          "name": "La locul de muncă"
        },
        {
          "language": "ru",
          "name": "На рабочем месте"
        },
        {
          "language": "sq",
          "name": "Në vendin e punës"
        },
        {
          "language": "tr",
          "name": "İş yeri"
        }
      ]
    },
    {
      "kind": "Usage",
      "key": "administrative",
      "displayName": "Administrative",
      "sortOrder": 120,
      "localizations": [
        {
          "language": "de",
          "name": "Administrativ"
        },
        {
          "language": "ar",
          "name": "إداري"
        },
        {
          "language": "ckb",
          "name": "کارگێڕی"
        },
        {
          "language": "en",
          "name": "Administrative"
        },
        {
          "language": "fa",
          "name": "اداری"
        },
        {
          "language": "kmr",
          "name": "Rêveberî"
        },
        {
          "language": "pl",
          "name": "Administracyjny"
        },
        {
          "language": "ro",
          "name": "Administrativ"
        },
        {
          "language": "ru",
          "name": "Административный"
        },
        {
          "language": "sq",
          "name": "Administrativ"
        },
        {
          "language": "tr",
          "name": "İdari"
        }
      ]
    },
    {
      "kind": "Usage",
      "key": "analysis",
      "displayName": "Analysis",
      "sortOrder": 200,
      "localizations": [
        {
          "language": "de",
          "name": "Analyse"
        },
        {
          "language": "ar",
          "name": "تحليل"
        },
        {
          "language": "ckb",
          "name": "شیکردنەوە"
        },
        {
          "language": "en",
          "name": "Analysis"
        },
        {
          "language": "fa",
          "name": "تحلیل"
        },
        {
          "language": "kmr",
          "name": "Analîz"
        },
        {
          "language": "pl",
          "name": "Analiza"
        },
        {
          "language": "ro",
          "name": "Analiză"
        },
        {
          "language": "ru",
          "name": "Анализ"
        },
        {
          "language": "sq",
          "name": "Analizë"
        },
        {
          "language": "tr",
          "name": "Analiz"
        }
      ]
    },
    {
      "kind": "Usage",
      "key": "process",
      "displayName": "Process-related",
      "sortOrder": 210,
      "localizations": [
        {
          "language": "de",
          "name": "Prozessbezogen"
        },
        {
          "language": "ar",
          "name": "متعلق بالعملية"
        },
        {
          "language": "ckb",
          "name": "پڕۆسەیی"
        },
        {
          "language": "en",
          "name": "Process-related"
        },
        {
          "language": "fa",
          "name": "فرایندی"
        },
        {
          "language": "kmr",
          "name": "Girêdayî pêvajoyê"
        },
        {
          "language": "pl",
          "name": "Procesowy"
        },
        {
          "language": "ro",
          "name": "Legat de proces"
        },
        {
          "language": "ru",
          "name": "Процессный"
        },
        {
          "language": "sq",
          "name": "I lidhur me procesin"
        },
        {
          "language": "tr",
          "name": "Süreçle ilgili"
        }
      ]
    }
  ],
  "entries": [
    {
      "word": "Fremdfertigungsbelegposition",
      "language": "de",
      "cefrLevel": "C1",
      "partOfSpeech": "Noun",
      "article": "die",
      "plural": "Fremdfertigungsbelegpositionen",
      "infinitive": null,
      "pronunciationIpa": null,
      "syllableBreak": "Fremd-fer-ti-gungs-be-leg-po-si-ti-on",
      "topics": [
        "production-and-maintenance",
        "documents-and-administration",
        "erp-and-business-systems"
      ],
      "usageLabels": [
        "business",
        "workplace",
        "process",
        "formal"
      ],
      "contextLabels": [],
      "grammarNotes": [
        "die noun; specialized ERP/business term"
      ],
      "collocations": [],
      "wordFamilies": [],
      "relations": [],
      "meanings": [
        {
          "language": "ar",
          "text": "بند مستند التصنيع الخارجي"
        },
        {
          "language": "ckb",
          "text": "بڕگەی بەڵگەی بەرهەمهێنانی دەرەکی"
        },
        {
          "language": "en",
          "text": "external manufacturing document line item"
        },
        {
          "language": "fa",
          "text": "ردیف سند تولید بیرونی"
        },
        {
          "language": "kmr",
          "text": "hêmana belgeya hilberîna derveyî"
        },
        {
          "language": "pl",
          "text": "pozycja dokumentu produkcji zewnętrznej"
        },
        {
          "language": "ro",
          "text": "poziție a documentului de producție externă"
        },
        {
          "language": "ru",
          "text": "позиция документа внешнего производства"
        },
        {
          "language": "sq",
          "text": "pozicion i dokumentit të prodhimit të jashtëm"
        },
        {
          "language": "tr",
          "text": "dış üretim belgesi kalemi"
        }
      ],
      "examples": [
        {
          "baseText": "Die Fremdfertigungsbelegposition zeigt im ERP, welche Komponente der Lieferant bearbeiten und in welcher Menge zurückliefern muss.",
          "translations": [
            {
              "language": "ar",
              "text": "يوضح بند مستند التصنيع الخارجي في ERP أي مكون يجب على المورد معالجته وبأي كمية إرجاعه."
            },
            {
              "language": "ckb",
              "text": "بڕگەی بەڵگەی بەرهەمهێنانی دەرەکی لە ERPدا نیشان دەدات دابینکەر کام پێکهاتە و بە چ بڕێک دەگەڕێنێتەوە."
            },
            {
              "language": "en",
              "text": "The external manufacturing document line item shows in ERP which component the supplier must process and in what quantity return it."
            },
            {
              "language": "fa",
              "text": "ردیف سند تولید بیرونی در ERP نشان می‌دهد تأمین‌کننده کدام قطعه را با چه مقداری باید پردازش و برگرداند."
            },
            {
              "language": "kmr",
              "text": "Hêmana belgeya hilberîna derveyî di ERP de nîşan dide dabînker kîjan pêkhate bi çi hejmarê vegerîne."
            },
            {
              "language": "pl",
              "text": "Pozycja dokumentu produkcji zewnętrznej pokazuje w ERP, który komponent dostawca ma obrobić i w jakiej ilości zwrócić."
            },
            {
              "language": "ro",
              "text": "Poziția documentului de producție externă arată în ERP ce componentă trebuie procesată de furnizor și în ce cantitate returnată."
            },
            {
              "language": "ru",
              "text": "Позиция документа внешнего производства показывает в ERP, какой компонент поставщик должен обработать и в каком количестве вернуть."
            },
            {
              "language": "sq",
              "text": "Pozicioni i dokumentit të prodhimit të jashtëm tregon në ERP cilin komponent duhet të përpunojë furnitori dhe në çfarë sasie ta kthejë."
            },
            {
              "language": "tr",
              "text": "Dış üretim belgesi kalemi ERP içinde tedarikçinin hangi bileşeni hangi miktarda işleyip geri göndermesi gerektiğini gösterir."
            }
          ]
        },
        {
          "baseText": "Bei der Reklamation war nur eine Fremdfertigungsbelegposition betroffen, deshalb blieb der restliche Auftrag lieferfähig.",
          "translations": [
            {
              "language": "ar",
              "text": "في الشكوى كان بند واحد فقط من مستند التصنيع الخارجي متأثرًا، لذلك بقي باقي الطلب قابلاً للتسليم."
            },
            {
              "language": "ckb",
              "text": "لە سکاڵاکەدا تەنها یەک بڕگەی بەڵگەی بەرهەمهێنانی دەرەکی کاریگەری وەرگرت، بۆیە داواکارییەکەی تر ئامادەی گەیاندن بوو."
            },
            {
              "language": "en",
              "text": "Only one external manufacturing document line item was affected by the complaint, so the rest of the order remained deliverable."
            },
            {
              "language": "fa",
              "text": "در شکایت فقط یک ردیف سند تولید بیرونی درگیر بود، بنابراین بقیه سفارش قابل تحویل ماند."
            },
            {
              "language": "kmr",
              "text": "Di gilîkirinê de tenê yek hêmana belgeyê bandor dît, ji ber vê yekê mayîya fermanê dikarî bê radestkirin."
            },
            {
              "language": "pl",
              "text": "Reklamacja dotyczyła tylko jednej pozycji dokumentu produkcji zewnętrznej, więc reszta zlecenia pozostała możliwa do dostawy."
            },
            {
              "language": "ro",
              "text": "În reclamație era afectată doar o poziție a documentului de producție externă, astfel restul comenzii a rămas livrabil."
            },
            {
              "language": "ru",
              "text": "В рекламации была затронута только одна позиция документа внешнего производства, поэтому остальная часть заказа осталась поставляемой."
            },
            {
              "language": "sq",
              "text": "Në ankesë u prek vetëm një pozicion i dokumentit të prodhimit të jashtëm, prandaj pjesa tjetër e porosisë mbeti e dorëzueshme."
            },
            {
              "language": "tr",
              "text": "Şikayette yalnızca bir dış üretim belgesi kalemi etkilendi, bu yüzden siparişin kalanı teslim edilebilir kaldı."
            }
          ]
        }
      ]
    },
    {
      "word": "Gruppierungsauftrag",
      "language": "de",
      "cefrLevel": "C1",
      "partOfSpeech": "Noun",
      "article": "der",
      "plural": "Gruppierungsaufträge",
      "infinitive": null,
      "pronunciationIpa": null,
      "syllableBreak": "Grup-pie-rungs-auf-trag",
      "topics": [
        "warehouse-and-logistics",
        "erp-and-business-systems",
        "planning-and-projects"
      ],
      "usageLabels": [
        "business",
        "workplace",
        "process",
        "administrative"
      ],
      "contextLabels": [],
      "grammarNotes": [
        "der noun; specialized ERP/business term"
      ],
      "collocations": [],
      "wordFamilies": [],
      "relations": [],
      "meanings": [
        {
          "language": "ar",
          "text": "أمر تجميع"
        },
        {
          "language": "ckb",
          "text": "فەرمانی گرووپکردن"
        },
        {
          "language": "en",
          "text": "grouping order"
        },
        {
          "language": "fa",
          "text": "دستور گروه‌بندی"
        },
        {
          "language": "kmr",
          "text": "fermana komkirinê"
        },
        {
          "language": "pl",
          "text": "zlecenie grupowania"
        },
        {
          "language": "ro",
          "text": "ordin de grupare"
        },
        {
          "language": "ru",
          "text": "заказ на группировку"
        },
        {
          "language": "sq",
          "text": "urdhër grupimi"
        },
        {
          "language": "tr",
          "text": "gruplama emri"
        }
      ],
      "examples": [
        {
          "baseText": "Der Gruppierungsauftrag fasst im ERP mehrere kleine Lieferungen zusammen, damit sie gemeinsam kommissioniert und verladen werden.",
          "translations": [
            {
              "language": "ar",
              "text": "يجمع أمر التجميع في ERP عدة تسليمات صغيرة كي يتم انتقاؤها وتحميلها معًا."
            },
            {
              "language": "ckb",
              "text": "فەرمانی گرووپکردن لە ERPدا چەند گەیاندنی بچووک کۆدەکاتەوە تاکو پێکەوە کۆبکرێنەوە و باربکرێن."
            },
            {
              "language": "en",
              "text": "The grouping order combines several small deliveries in ERP so they can be picked and loaded together."
            },
            {
              "language": "fa",
              "text": "دستور گروه‌بندی در ERP چند تحویل کوچک را جمع می‌کند تا با هم برداشت و بارگیری شوند."
            },
            {
              "language": "kmr",
              "text": "Fermana komkirinê di ERP de çend radestkirinên biçûk dicivîne da bi hev re bên komkirin û barkirin."
            },
            {
              "language": "pl",
              "text": "Zlecenie grupowania łączy w ERP kilka małych dostaw, aby można je było razem skompletować i załadować."
            },
            {
              "language": "ro",
              "text": "Ordinul de grupare combină în ERP mai multe livrări mici pentru a fi pregătite și încărcate împreună."
            },
            {
              "language": "ru",
              "text": "Заказ на группировку объединяет в ERP несколько небольших поставок для совместного подбора и погрузки."
            },
            {
              "language": "sq",
              "text": "Urdhri i grupimit bashkon në ERP disa dërgesa të vogla që të përzgjidhen dhe ngarkohen së bashku."
            },
            {
              "language": "tr",
              "text": "Gruplama emri ERP içinde birkaç küçük teslimatı birlikte toplamak ve yüklemek için birleştirir."
            }
          ]
        },
        {
          "baseText": "Der Disponent löste den Gruppierungsauftrag auf, weil ein Kunde eine Teillieferung früher benötigte.",
          "translations": [
            {
              "language": "ar",
              "text": "حل المخطط أمر التجميع لأن أحد العملاء احتاج إلى تسليم جزئي في وقت أبكر."
            },
            {
              "language": "ckb",
              "text": "پلاندانەر فەرمانی گرووپکردنی هەڵوەشاندەوە چونکە کڕیارێک بەشێک لە گەیاندنەکەی زووتر پێویست بوو."
            },
            {
              "language": "en",
              "text": "The planner dissolved the grouping order because one customer needed a partial delivery earlier."
            },
            {
              "language": "fa",
              "text": "برنامه‌ریز دستور گروه‌بندی را باز کرد چون یک مشتری تحویل بخشی را زودتر می‌خواست."
            },
            {
              "language": "kmr",
              "text": "Plansaz fermana komkirinê betal kir ji ber ku xerîdarek radestkirina qismî zûtir dixwest."
            },
            {
              "language": "pl",
              "text": "Planista rozwiązał zlecenie grupowania, ponieważ klient potrzebował wcześniejszej dostawy częściowej."
            },
            {
              "language": "ro",
              "text": "Planificatorul a desființat ordinul de grupare deoarece un client avea nevoie mai devreme de o livrare parțială."
            },
            {
              "language": "ru",
              "text": "Планировщик расформировал заказ на группировку, потому что клиенту требовалась частичная поставка раньше."
            },
            {
              "language": "sq",
              "text": "Planifikuesi e shpërbëri urdhrin e grupimit sepse një klient kishte nevojë më herët për dorëzim të pjesshëm."
            },
            {
              "language": "tr",
              "text": "Planlamacı gruplama emrini dağıttı, çünkü bir müşteri kısmi teslimatı daha erken istedi."
            }
          ]
        }
      ]
    },
    {
      "word": "Gruppierungsbezeichnung",
      "language": "de",
      "cefrLevel": "C1",
      "partOfSpeech": "Noun",
      "article": "die",
      "plural": "Gruppierungsbezeichnungen",
      "infinitive": null,
      "pronunciationIpa": null,
      "syllableBreak": "Grup-pie-rungs-be-zeich-nung",
      "topics": [
        "erp-and-business-systems",
        "data-and-reporting",
        "documents-and-administration"
      ],
      "usageLabels": [
        "business",
        "workplace",
        "administrative",
        "analysis"
      ],
      "contextLabels": [],
      "grammarNotes": [
        "die noun; specialized ERP/business term"
      ],
      "collocations": [],
      "wordFamilies": [],
      "relations": [],
      "meanings": [
        {
          "language": "ar",
          "text": "تسمية المجموعة"
        },
        {
          "language": "ckb",
          "text": "ناونیشانی گرووپکردن"
        },
        {
          "language": "en",
          "text": "grouping label"
        },
        {
          "language": "fa",
          "text": "عنوان گروه‌بندی"
        },
        {
          "language": "kmr",
          "text": "navê komkirinê"
        },
        {
          "language": "pl",
          "text": "nazwa grupowania"
        },
        {
          "language": "ro",
          "text": "denumire de grupare"
        },
        {
          "language": "ru",
          "text": "обозначение группировки"
        },
        {
          "language": "sq",
          "text": "emërtim grupimi"
        },
        {
          "language": "tr",
          "text": "gruplama adı"
        }
      ],
      "examples": [
        {
          "baseText": "Die Gruppierungsbezeichnung muss im ERP eindeutig sein, damit Lager und Versand dieselbe Sammelbewegung erkennen.",
          "translations": [
            {
              "language": "ar",
              "text": "يجب أن تكون تسمية المجموعة في ERP واضحة كي يتعرف المستودع والشحن على نفس الحركة المجمعة."
            },
            {
              "language": "ckb",
              "text": "ناونیشانی گرووپکردن لە ERPدا دەبێت ڕوون بێت تاکو کۆگا و ناردن هەمان جووڵەی کۆکراو بناسن."
            },
            {
              "language": "en",
              "text": "The grouping label must be unique in ERP so warehouse and shipping recognize the same consolidated movement."
            },
            {
              "language": "fa",
              "text": "عنوان گروه‌بندی در ERP باید یکتا باشد تا انبار و ارسال همان حرکت تجمیعی را تشخیص دهند."
            },
            {
              "language": "kmr",
              "text": "Navê komkirinê di ERP de divê yekta be da depo û şandin heman tevgera komkirî nas bikin."
            },
            {
              "language": "pl",
              "text": "Nazwa grupowania musi być w ERP jednoznaczna, aby magazyn i wysyłka rozpoznawały ten sam ruch zbiorczy."
            },
            {
              "language": "ro",
              "text": "Denumirea de grupare trebuie să fie unică în ERP pentru ca depozitul și expedierea să recunoască aceeași mișcare consolidată."
            },
            {
              "language": "ru",
              "text": "Обозначение группировки должно быть уникальным в ERP, чтобы склад и отгрузка распознавали одно и то же объединенное движение."
            },
            {
              "language": "sq",
              "text": "Emërtimi i grupimit duhet të jetë unik në ERP që magazina dhe dërgesa të njohin të njëjtën lëvizje të konsoliduar."
            },
            {
              "language": "tr",
              "text": "Gruplama adı ERP içinde benzersiz olmalıdır, böylece depo ve sevkiyat aynı toplu hareketi tanır."
            }
          ]
        },
        {
          "baseText": "Nach mehreren Rückfragen änderte das Projektteam die Gruppierungsbezeichnung, weil die alte Abkürzung im Vertrieb missverstanden wurde.",
          "translations": [
            {
              "language": "ar",
              "text": "بعد عدة استفسارات غيّر فريق المشروع تسمية المجموعة لأن الاختصار القديم فُهم خطأ في المبيعات."
            },
            {
              "language": "ckb",
              "text": "دوای چەند پرسیار، تیمی پڕۆژە ناونیشانی گرووپکردنی گۆڕی چونکە کورتکراوەی کۆن لە فرۆشتندا بە هەڵە تێگەیشترابوو."
            },
            {
              "language": "en",
              "text": "After several questions, the project team changed the grouping label because the old abbreviation was misunderstood in sales."
            },
            {
              "language": "fa",
              "text": "بعد از چند پرسش، تیم پروژه عنوان گروه‌بندی را تغییر داد چون مخفف قبلی در فروش بد فهمیده شده بود."
            },
            {
              "language": "kmr",
              "text": "Piştî çend pirsan, tîma projeyê navê komkirinê guherand ji ber ku kurtkirina kevn di firotanê de şaş hatibû fêmkirin."
            },
            {
              "language": "pl",
              "text": "Po kilku pytaniach zespół projektu zmienił nazwę grupowania, ponieważ stary skrót był źle rozumiany w sprzedaży."
            },
            {
              "language": "ro",
              "text": "După mai multe întrebări, echipa de proiect a schimbat denumirea de grupare, deoarece vechea abreviere era înțeleasă greșit în vânzări."
            },
            {
              "language": "ru",
              "text": "После нескольких вопросов проектная команда изменила обозначение группировки, потому что старую аббревиатуру неправильно понимали в продажах."
            },
            {
              "language": "sq",
              "text": "Pas disa pyetjesh, ekipi i projektit ndryshoi emërtimin e grupimit sepse shkurtesa e vjetër keqkuptohej në shitje."
            },
            {
              "language": "tr",
              "text": "Birkaç sorudan sonra proje ekibi gruplama adını değiştirdi, çünkü eski kısaltma satışta yanlış anlaşılıyordu."
            }
          ]
        }
      ]
    },
    {
      "word": "Gruppierungsreihenfolge",
      "language": "de",
      "cefrLevel": "C1",
      "partOfSpeech": "Noun",
      "article": "die",
      "plural": "Gruppierungsreihenfolgen",
      "infinitive": null,
      "pronunciationIpa": null,
      "syllableBreak": "Grup-pie-rungs-rei-hen-fol-ge",
      "topics": [
        "erp-and-business-systems",
        "warehouse-and-logistics",
        "data-and-reporting"
      ],
      "usageLabels": [
        "business",
        "workplace",
        "process",
        "analysis"
      ],
      "contextLabels": [],
      "grammarNotes": [
        "die noun; specialized ERP/business term"
      ],
      "collocations": [],
      "wordFamilies": [],
      "relations": [],
      "meanings": [
        {
          "language": "ar",
          "text": "ترتيب التجميع"
        },
        {
          "language": "ckb",
          "text": "ڕیزبەندی گرووپکردن"
        },
        {
          "language": "en",
          "text": "grouping sequence"
        },
        {
          "language": "fa",
          "text": "ترتیب گروه‌بندی"
        },
        {
          "language": "kmr",
          "text": "rêza komkirinê"
        },
        {
          "language": "pl",
          "text": "kolejność grupowania"
        },
        {
          "language": "ro",
          "text": "ordine de grupare"
        },
        {
          "language": "ru",
          "text": "последовательность группировки"
        },
        {
          "language": "sq",
          "text": "rend grupimi"
        },
        {
          "language": "tr",
          "text": "gruplama sırası"
        }
      ],
      "examples": [
        {
          "baseText": "Die Gruppierungsreihenfolge bestimmt im ERP, ob Aufträge zuerst nach Tour, Kunde oder Liefertermin zusammengefasst werden.",
          "translations": [
            {
              "language": "ar",
              "text": "يحدد ترتيب التجميع في ERP ما إذا كانت الطلبات تُجمع أولًا حسب الجولة أو العميل أو موعد التسليم."
            },
            {
              "language": "ckb",
              "text": "ڕیزبەندی گرووپکردن لە ERPدا دیاری دەکات داواکارییەکان سەرەتا بەپێی گەشت، کڕیار یان کاتی گەیاندن کۆبکرێنەوە."
            },
            {
              "language": "en",
              "text": "The grouping sequence determines in ERP whether orders are first combined by route, customer, or delivery date."
            },
            {
              "language": "fa",
              "text": "ترتیب گروه‌بندی در ERP تعیین می‌کند سفارش‌ها ابتدا بر اساس مسیر، مشتری یا تاریخ تحویل تجمیع شوند."
            },
            {
              "language": "kmr",
              "text": "Rêza komkirinê di ERP de diyar dike ka ferman pêşî li gorî rê, xerîdar an roja radestkirinê bên komkirin."
            },
            {
              "language": "pl",
              "text": "Kolejność grupowania określa w ERP, czy zlecenia są najpierw łączone według trasy, klienta czy terminu dostawy."
            },
            {
              "language": "ro",
              "text": "Ordinea de grupare stabilește în ERP dacă comenzile sunt combinate mai întâi după rută, client sau termen de livrare."
            },
            {
              "language": "ru",
              "text": "Последовательность группировки определяет в ERP, объединяются ли заказы сначала по маршруту, клиенту или дате поставки."
            },
            {
              "language": "sq",
              "text": "Rendi i grupimit përcakton në ERP nëse porositë bashkohen fillimisht sipas turit, klientit apo datës së dorëzimit."
            },
            {
              "language": "tr",
              "text": "Gruplama sırası ERP içinde siparişlerin önce rota, müşteri veya teslim tarihine göre birleştirilip birleştirilmeyeceğini belirler."
            }
          ]
        },
        {
          "baseText": "Eine falsche Gruppierungsreihenfolge führte dazu, dass eilige Kundenaufträge hinter weniger kritischen Lagerbewegungen landeten.",
          "translations": [
            {
              "language": "ar",
              "text": "أدى ترتيب تجميع خاطئ إلى وضع طلبات العملاء العاجلة خلف حركات مخزون أقل أهمية."
            },
            {
              "language": "ckb",
              "text": "ڕیزبەندی هەڵەی گرووپکردن وای کرد داواکارییە پەلەکانی کڕیار لە دوای جووڵەی کۆگای کەمتر گرنگ بکەون."
            },
            {
              "language": "en",
              "text": "An incorrect grouping sequence caused urgent customer orders to end up behind less critical warehouse movements."
            },
            {
              "language": "fa",
              "text": "ترتیب گروه‌بندی اشتباه باعث شد سفارش‌های فوری مشتری پشت حرکات انباری کم‌اهمیت‌تر قرار بگیرند."
            },
            {
              "language": "kmr",
              "text": "Rêza şaş a komkirinê bû sedem ku fermanên lezgîn ên xerîdar li pişt tevgerên depoyê yên kêmtir girîng bikevin."
            },
            {
              "language": "pl",
              "text": "Błędna kolejność grupowania sprawiła, że pilne zamówienia klientów znalazły się za mniej krytycznymi ruchami magazynowymi."
            },
            {
              "language": "ro",
              "text": "O ordine greșită de grupare a făcut ca comenzile urgente ale clienților să ajungă după mișcări de stoc mai puțin critice."
            },
            {
              "language": "ru",
              "text": "Неверная последовательность группировки привела к тому, что срочные заказы клиентов оказались за менее критичными складскими движениями."
            },
            {
              "language": "sq",
              "text": "Një rend i gabuar grupimi bëri që porositë urgjente të klientëve të mbeteshin pas lëvizjeve më pak kritike të magazinës."
            },
            {
              "language": "tr",
              "text": "Yanlış gruplama sırası acil müşteri siparişlerinin daha az kritik depo hareketlerinin arkasına düşmesine yol açtı."
            }
          ]
        }
      ]
    },
    {
      "word": "Gruppierungszuordnung",
      "language": "de",
      "cefrLevel": "C1",
      "partOfSpeech": "Noun",
      "article": "die",
      "plural": "Gruppierungszuordnungen",
      "infinitive": null,
      "pronunciationIpa": null,
      "syllableBreak": "Grup-pie-rungs-zu-ord-nung",
      "topics": [
        "erp-and-business-systems",
        "warehouse-and-logistics",
        "documents-and-administration"
      ],
      "usageLabels": [
        "business",
        "workplace",
        "process",
        "administrative"
      ],
      "contextLabels": [],
      "grammarNotes": [
        "die noun; specialized ERP/business term"
      ],
      "collocations": [],
      "wordFamilies": [],
      "relations": [],
      "meanings": [
        {
          "language": "ar",
          "text": "تخصيص التجميع"
        },
        {
          "language": "ckb",
          "text": "تەرخانکردنی گرووپکردن"
        },
        {
          "language": "en",
          "text": "grouping assignment"
        },
        {
          "language": "fa",
          "text": "تخصیص گروه‌بندی"
        },
        {
          "language": "kmr",
          "text": "tayînkirina komkirinê"
        },
        {
          "language": "pl",
          "text": "przypisanie grupowania"
        },
        {
          "language": "ro",
          "text": "alocare de grupare"
        },
        {
          "language": "ru",
          "text": "назначение группировки"
        },
        {
          "language": "sq",
          "text": "caktim grupimi"
        },
        {
          "language": "tr",
          "text": "gruplama ataması"
        }
      ],
      "examples": [
        {
          "baseText": "Die Gruppierungszuordnung legt im ERP fest, welche Lieferpositionen gemeinsam auf eine Sammelliste übernommen werden.",
          "translations": [
            {
              "language": "ar",
              "text": "يحدد تخصيص التجميع في ERP أي بنود تسليم تُنقل معًا إلى قائمة تجميع."
            },
            {
              "language": "ckb",
              "text": "تەرخانکردنی گرووپکردن لە ERPدا دیاری دەکات کام بڕگەکانی گەیاندن پێکەوە دەچنە ناو لیستی کۆکردنەوە."
            },
            {
              "language": "en",
              "text": "The grouping assignment defines in ERP which delivery line items are transferred together to a consolidated list."
            },
            {
              "language": "fa",
              "text": "تخصیص گروه‌بندی در ERP مشخص می‌کند کدام ردیف‌های تحویل با هم به لیست تجمیعی منتقل شوند."
            },
            {
              "language": "kmr",
              "text": "Tayînkirina komkirinê di ERP de diyar dike kîjan hêmayên radestkirinê bi hev re derbasî lîsteya komkirî dibin."
            },
            {
              "language": "pl",
              "text": "Przypisanie grupowania określa w ERP, które pozycje dostaw trafiają razem na listę zbiorczą."
            },
            {
              "language": "ro",
              "text": "Alocarea de grupare stabilește în ERP ce poziții de livrare sunt transferate împreună pe o listă consolidată."
            },
            {
              "language": "ru",
              "text": "Назначение группировки определяет в ERP, какие позиции поставки вместе переносятся в сводный список."
            },
            {
              "language": "sq",
              "text": "Caktimi i grupimit përcakton në ERP cilat pozicione dorëzimi kalojnë së bashku në listën e konsoliduar."
            },
            {
              "language": "tr",
              "text": "Gruplama ataması ERP içinde hangi teslimat kalemlerinin toplu listeye birlikte aktarılacağını belirler."
            }
          ]
        },
        {
          "baseText": "Bei der Prozessanalyse zeigte sich, dass mehrere Gruppierungszuordnungen historisch gewachsen und fachlich nicht mehr begründet waren.",
          "translations": [
            {
              "language": "ar",
              "text": "في تحليل العملية ظهر أن عدة تخصيصات تجميع نشأت تاريخيًا ولم تعد مبررة من الناحية المهنية."
            },
            {
              "language": "ckb",
              "text": "لە شیکردنەوەی پڕۆسەدا دەرکەوت چەند تەرخانکردنی گرووپکردن بە مێژوویی گەشەیان کردووە و چیتر پاساوی پیشەییان نییە."
            },
            {
              "language": "en",
              "text": "The process analysis showed that several grouping assignments had grown historically and were no longer justified from a business perspective."
            },
            {
              "language": "fa",
              "text": "در تحلیل فرایند مشخص شد چند تخصیص گروه‌بندی به مرور شکل گرفته‌اند و دیگر از نظر کاری توجیه ندارند."
            },
            {
              "language": "kmr",
              "text": "Analîza pêvajoyê nîşan da ku çend tayînkirinên komkirinê bi demê re çêbûne û êdî hinceta pisporî tune ye."
            },
            {
              "language": "pl",
              "text": "Analiza procesu pokazała, że kilka przypisań grupowania narastało historycznie i nie miało już uzasadnienia biznesowego."
            },
            {
              "language": "ro",
              "text": "Analiza procesului a arătat că mai multe alocări de grupare au crescut istoric și nu mai erau justificate profesional."
            },
            {
              "language": "ru",
              "text": "Анализ процесса показал, что несколько назначений группировки исторически сложились и больше не имели бизнес-обоснования."
            },
            {
              "language": "sq",
              "text": "Analiza e procesit tregoi se disa caktime grupimi ishin krijuar historikisht dhe nuk justifikoheshin më profesionalisht."
            },
            {
              "language": "tr",
              "text": "Süreç analizi bazı gruplama atamalarının tarihsel olarak oluştuğunu ve artık iş açısından gerekçeli olmadığını gösterdi."
            }
          ]
        }
      ]
    },
    {
      "word": "Handelsstückliste",
      "language": "de",
      "cefrLevel": "C1",
      "partOfSpeech": "Noun",
      "article": "die",
      "plural": "Handelsstücklisten",
      "infinitive": null,
      "pronunciationIpa": null,
      "syllableBreak": "Han-dels-stück-lis-te",
      "topics": [
        "sales-and-customers",
        "erp-and-business-systems",
        "warehouse-and-logistics"
      ],
      "usageLabels": [
        "business",
        "workplace",
        "process",
        "administrative"
      ],
      "contextLabels": [],
      "grammarNotes": [
        "die noun; specialized ERP/business term"
      ],
      "collocations": [],
      "wordFamilies": [],
      "relations": [],
      "meanings": [
        {
          "language": "ar",
          "text": "قائمة مكونات تجارية"
        },
        {
          "language": "ckb",
          "text": "لیستی پارچەکانی بازرگانی"
        },
        {
          "language": "en",
          "text": "commercial bill of materials"
        },
        {
          "language": "fa",
          "text": "لیست مواد تجاری"
        },
        {
          "language": "kmr",
          "text": "lîsteya parçeyên bazirganiyê"
        },
        {
          "language": "pl",
          "text": "handlowa lista materiałowa"
        },
        {
          "language": "ro",
          "text": "listă comercială de materiale"
        },
        {
          "language": "ru",
          "text": "торговая спецификация материалов"
        },
        {
          "language": "sq",
          "text": "listë tregtare materialesh"
        },
        {
          "language": "tr",
          "text": "ticari ürün ağacı"
        }
      ],
      "examples": [
        {
          "baseText": "Die Handelsstückliste bündelt im ERP mehrere Artikel zu einem verkaufsfähigen Set, ohne dass dafür ein Produktionsauftrag entsteht.",
          "translations": [
            {
              "language": "ar",
              "text": "تجمع قائمة المكونات التجارية في ERP عدة أصناف في مجموعة قابلة للبيع من دون إنشاء أمر إنتاج."
            },
            {
              "language": "ckb",
              "text": "لیستی پارچەکانی بازرگانی لە ERPدا چەند کاڵا دەکاتە سێتێکی فرۆشتن، بەبێ ئەوەی فەرمانی بەرهەمهێنان دروست بێت."
            },
            {
              "language": "en",
              "text": "The commercial bill of materials bundles several items into a sellable set in ERP without creating a production order."
            },
            {
              "language": "fa",
              "text": "لیست مواد تجاری در ERP چند کالا را به یک بسته قابل فروش تبدیل می‌کند بدون اینکه سفارش تولید ایجاد شود."
            },
            {
              "language": "kmr",
              "text": "Lîsteya parçeyên bazirganiyê di ERP de çend gotar dike setek firotanî bêyî fermana hilberînê."
            },
            {
              "language": "pl",
              "text": "Handlowa lista materiałowa łączy w ERP kilka artykułów w zestaw sprzedażowy bez tworzenia zlecenia produkcyjnego."
            },
            {
              "language": "ro",
              "text": "Lista comercială de materiale grupează în ERP mai multe articole într-un set vandabil fără comandă de producție."
            },
            {
              "language": "ru",
              "text": "Торговая спецификация объединяет в ERP несколько товаров в продаваемый набор без создания производственного заказа."
            },
            {
              "language": "sq",
              "text": "Lista tregtare e materialeve bashkon në ERP disa artikuj në një set të shitshëm pa krijuar urdhër prodhimi."
            },
            {
              "language": "tr",
              "text": "Ticari ürün ağacı ERP içinde birkaç ürünü üretim emri oluşturmadan satılabilir bir sete dönüştürür."
            }
          ]
        },
        {
          "baseText": "Der Kundenservice prüfte die Handelsstückliste, weil im Angebot ein Zubehörteil fehlte, das im Set eigentlich enthalten sein sollte.",
          "translations": [
            {
              "language": "ar",
              "text": "فحصت خدمة العملاء قائمة المكونات التجارية لأن جزءًا من الملحقات كان مفقودًا في العرض رغم أنه يجب أن يكون ضمن المجموعة."
            },
            {
              "language": "ckb",
              "text": "خزمەتگوزاری کڕیار لیستی پارچەکانی بازرگانی پشکنینی کرد چونکە پارچەیەکی هاوپێچ لە پێشنیاردا نەبوو."
            },
            {
              "language": "en",
              "text": "Customer service checked the commercial bill of materials because an accessory was missing from the quote although it should have been included in the set."
            },
            {
              "language": "fa",
              "text": "خدمات مشتری لیست مواد تجاری را بررسی کرد چون یک قطعه جانبی در پیشنهاد نبود، در حالی که باید داخل بسته می‌بود."
            },
            {
              "language": "kmr",
              "text": "Xizmeta xerîdar lîsteya parçeyan kontrol kir ji ber ku pêveka di pêşniyarê de kêm bû."
            },
            {
              "language": "pl",
              "text": "Obsługa klienta sprawdziła handlową listę materiałową, ponieważ w ofercie brakowało akcesorium należącego do zestawu."
            },
            {
              "language": "ro",
              "text": "Serviciul clienți a verificat lista comercială deoarece lipsea un accesoriu care trebuia inclus în set."
            },
            {
              "language": "ru",
              "text": "Служба клиентов проверила торговую спецификацию, потому что в предложении не хватало аксессуара, который должен был входить в набор."
            },
            {
              "language": "sq",
              "text": "Shërbimi ndaj klientit kontrolloi listën tregtare sepse mungonte një aksesor që duhej të ishte në set."
            },
            {
              "language": "tr",
              "text": "Müşteri hizmetleri ticari ürün ağacını kontrol etti, çünkü teklifte sette olması gereken bir aksesuar eksikti."
            }
          ]
        }
      ]
    }
  ],
  "collections": [],
  "scenarios": [],
  "conversationStarterPacks": [],
  "eventPreparationPacks": []
}